{
    "Баклажан": "Eggplant",
    "Яблуко": "Apple",
    "Базилік": "Basil",
    "Болгарський перець": "Bell Pepper",
    "Каперси": "Capers",
    "Селера": "Celery",
    "Мангольд": "Swiss Chard",
    "Сир фєта": "Feta Cheese",
    "Анчоуси": "Anchovies",
    "Артішок": "Artichoke",
    "Хліб": "Bread",
    "Піта": "Pita",
    "Панірувальні сухарі": "Breadcrumbs",
    "Капуста": "Cabbage",
    "Кешʼю": "Cashew",
    "Сир емменталь": "Emmental Cheese",
    "Козиний сир": "Goat Cheese",
    "Сир грюєр": "Gruyere",
    "Моцарелла": "Mozzarella",
    "Пармезан": "Parmesan",
    "Рікотта": "Ricotta",
    "Кабачок": "Zucchini",
    "Кориця": "Cinnamon",
    "Кус-кус": "Couscous",
    "Яйця": "Eggs",
    "Окунь": "Perch",
    "Сочевиця": "Lentils",
    "Свинина": "Pork",
    "Розмарин": "Rosemary",
    "Лосось": "Salmon",
    "Креветки": "Shrimp",
    "Кокос": "Coconut",
    "Вершки": "Cream",
    "Цибуля": "Onion",
    "Орегано": "Oregano",
    "Томат": "Tomato",
    "Куркума": "Turmeric",
    "Йогурт": "Yogurt",
    "Мандарин": "Mandarin",
    "Курка": "Chicken",
    "Бульон": "Broth",
    "Борошно": "Flour",
    "Кукурудза": "Corn",
    "Яловичина": "Beef",
    "Чорна Квасоля": "Black Beans",
    "Біла квасоля": "White Beans",
    "Боби едамаме": "Edamame Beans",
    "Зелена квасоля": "Green Beans",
    "Червона квасоля": "Red Beans",
    "Булгур": "Bulgur",
    "Буррата": "Burrata",
    "Курага": "Dried Apricots",
    "Авокадо": "Avocado",
    "Бекон": "Bacon",
    "Пиво": "Beer",
    "Бренді": "Brandy",
    "Морква": "Carrot",
    "Цвітна капуста": "Cauliflower",
    "Блакитний сир": "Blue Cheese",
    "Куряча печінка": "Chicken Liver",
    "Кокосове молоко": "Coconut Milk",
    "Сметана": "Sour Cream",
    "Каррі": "Curry",
    "Інжир": "Fig",
    "Часник": "Garlic"
}